peak/__init__.py
peak/_metadata.py
peak/_version.py
peak/auth.py
peak/base_client.py
peak/callbacks.py
peak/cli/__init_.py
peak/cli/args.py
peak/cli/cli.py
peak/cli/helpers.py
peak/cli/metrics/__init__.py
peak/cli/metrics/metrics.py
peak/cli/press/__init__.py
peak/cli/press/apps/__init__.py
peak/cli/press/apps/deployments.py
peak/cli/press/apps/specs.py
peak/cli/press/blocks/__init__.py
peak/cli/press/blocks/deployments.py
peak/cli/press/blocks/specs.py
peak/cli/press/deployments.py
peak/cli/press/specs.py
peak/cli/resources/__init__.py
peak/cli/resources/alerts/__init__.py
peak/cli/resources/alerts/emails.py
peak/cli/resources/artifacts.py
peak/cli/resources/cache.py
peak/cli/resources/images.py
peak/cli/resources/services.py
peak/cli/resources/tenants.py
peak/cli/resources/users.py
peak/cli/resources/webapps.py
peak/cli/resources/workflows.py
peak/cli/ruff.toml
peak/cli/version.py
peak/compression.py
peak/config.py
peak/constants.py
peak/decorators/__init__.py
peak/decorators/decorator.py
peak/decorators/exceptions.py
peak/decorators/inmemory_cache.py
peak/decorators/repository.py
peak/decorators/utils.py
peak/exceptions.py
peak/handler.py
peak/helpers.py
peak/logger.py
peak/metrics/__init__.py
peak/metrics/metrics.py
peak/output.py
peak/press/__init__.py
peak/press/apps.py
peak/press/blocks.py
peak/press/deployments.py
peak/press/specs.py
peak/py.typed
peak/resources/__init__.py
peak/resources/alerts.py
peak/resources/artifacts.py
peak/resources/cache.py
peak/resources/images.py
peak/resources/services.py
peak/resources/tenants.py
peak/resources/users.py
peak/resources/webapps.py
peak/resources/workflows.py
peak/sample_yaml/metrics/create_collection.yaml
peak/sample_yaml/metrics/publish.yaml
peak/sample_yaml/metrics/query.yaml
peak/sample_yaml/metrics/update-namespace.yaml
peak/sample_yaml/press/apps/deployments/create_app_deployment.yaml
peak/sample_yaml/press/apps/deployments/create_app_deployment_revision.yaml
peak_sdk-1.23.0.dist-info/LICENSE
peak_sdk-1.23.0.dist-info/METADATA
peak_sdk-1.23.0.dist-info/WHEEL
peak_sdk-1.23.0.dist-info/entry_points.txt
peak_sdk-1.23.0.dist-info/RECORD
