Metadata-Version: 2.1
Name: peak-sdk
Version: 1.23.0
Summary: Python SDK for interacting with the Peak platform
Home-page: https://docs.peak.ai/sdk/latest/
License: Apache-2.0
Author: Peak
Author-email: support@peak.ai
Requires-Python: >=3.8.1,<3.13
Classifier: Development Status :: 5 - Production/Stable
Classifier: Intended Audience :: Developers
Classifier: License :: OSI Approved :: Apache Software License
Classifier: Natural Language :: English
Classifier: Operating System :: OS Independent
Classifier: Programming Language :: Python :: 3
Classifier: Programming Language :: Python :: 3.9
Classifier: Programming Language :: Python :: 3.10
Classifier: Programming Language :: Python :: 3.11
Classifier: Programming Language :: Python :: 3.12
Classifier: Programming Language :: Python :: 3.8
Classifier: Topic :: Software Development :: Libraries :: Application Frameworks
Classifier: Typing :: Typed
Provides-Extra: types
Requires-Dist: cachetools (>=5.5.1,<6.0.0)
Requires-Dist: certifi (>=2024.2.2)
Requires-Dist: jinja2 (>=3.1,<4.0)
Requires-Dist: numpy ; extra == "types"
Requires-Dist: orjson (>=3.10,<4.0)
Requires-Dist: pandas ; extra == "types"
Requires-Dist: pathspec
Requires-Dist: pyyaml (>=6.0,<7.0)
Requires-Dist: requests (>=2.32,<3.0)
Requires-Dist: requests-toolbelt (>=1.0,<2.0)
Requires-Dist: rich (==14.0.0)
Requires-Dist: shellingham (<1.5.4)
Requires-Dist: structlog (>=24.2.0,<25.0.0)
Requires-Dist: typer (>=0.15.4,<0.16.0)
Requires-Dist: urllib3 (<2)
Requires-Dist: valkey (>=6.0.0,<7.0.0)
Project-URL: Documentation, https://docs.peak.ai/sdk/latest/
